samgenericservices/BaseMicroService.py
samgenericservices/FAAPIService.py
samgenericservices/IQNFCService.py
samgenericservices/__init__.py
samgenericservices-0.9.16.dist-info/LICENSE.txt
samgenericservices-0.9.16.dist-info/METADATA
samgenericservices-0.9.16.dist-info/WHEEL
samgenericservices-0.9.16.dist-info/top_level.txt
samgenericservices-0.9.16.dist-info/RECORD
