Metadata-Version: 2.1
Name: samgenericservices
Version: 0.9.16
Summary: Classes and functions to use for development of intregration software
Home-page: https://t.me/samthesuperhero
Author: Pavel A. Fomin
Author-email: fomin-p@yandex.ru
License: Creative Commons Attribution 4.0 International
Classifier: Development Status :: 4 - Beta
Classifier: Environment :: Other Environment
Classifier: License :: Other/Proprietary License
Classifier: Natural Language :: English
Classifier: Programming Language :: Python :: 3
Classifier: Programming Language :: Python :: 3.8
Classifier: Topic :: Utilities
Requires-Python: >=3.8
License-File: LICENSE.txt
Requires-Dist: aiohttp (>=3.8.4)
Requires-Dist: aio-pika (>=9.0.5)
Requires-Dist: aiormq (>=6.7.4)
Requires-Dist: asyncpg (>=0.27.0)
Requires-Dist: boto3 (>=1.22.8)
Requires-Dist: botocore (>=1.25.8)
Requires-Dist: bs4 (>=0.0.1)
Requires-Dist: multidict (>=6.0.4)
Requires-Dist: viledatools (>=1.0.34)
